src/tmx_to_text/converttmx.py
src/tmx_to_text/infotmx.py
src/tmx_to_text/tmx_to_text.py
tmx_to_text-0.1.8.dist-info/METADATA
tmx_to_text-0.1.8.dist-info/WHEEL
tmx_to_text-0.1.8.dist-info/entry_points.txt
tmx_to_text-0.1.8.dist-info/top_level.txt
tmx_to_text-0.1.8.dist-info/RECORD
