Metadata-Version: 2.1
Name: tmx-to-text
Version: 0.1.8
Summary: Converts TMX files to text files
Home-page: https://github.com/jordimas/tmx-to-text
Author: Jordi Mas
Author-email: jmas@softcatala.org
License: GPLv2+
Classifier: License :: OSI Approved :: GNU General Public License v2 or later (GPLv2+)
Classifier: Programming Language :: Python :: 3.6
Classifier: Programming Language :: Python :: 3.7
Classifier: Programming Language :: Python :: 3.8
Classifier: Programming Language :: Python :: 3.9
Classifier: Programming Language :: Python :: 3.10
Classifier: Programming Language :: Python :: 3.11
Classifier: Programming Language :: Python :: 3.12
Requires-Dist: lxml
